Metadata-Version: 1.1
Name: mpm
Version: 0.1.0.dev0
Summary: package (skill) manager for Misty
Home-page: https://github.com/rerobots/MistyPackageManager
Author: mpm contributors
Author-email: q@rerobots.net
License: Apache-2.0
Platform: UNKNOWN
Classifier: License :: OSI Approved :: Apache Software License
Classifier: Development Status :: 4 - Beta
Classifier: Programming Language :: Python :: 2.7
Classifier: Programming Language :: Python :: 3
Classifier: Programming Language :: Python :: 3.4
Classifier: Programming Language :: Python :: 3.5
Classifier: Programming Language :: Python :: 3.6
Classifier: Programming Language :: Python :: 3.7
Classifier: Programming Language :: Python :: 3.8
